Workbook

Sheet Start_Here
A1: NANODEGREE INTEGRATED EXCEL CAPSTONE This workbook ties together themes from the Data Analyst Nanodegree practice sets: marketing KPIs (CTR, CPC, CPL), P&L and gross margin, sales capacity forecasting, stickiness (DAU/MAU), monthly unit economics and cost per lead, exploratory analysis on MLB salaries, and geography lookups. HOW TO USE IT 1. Work through sheets in the suggested order below. Yellow cells are inputs you may change for what-if analysis; green-tinted areas are calculation zones (verify or extend formulas). 2. On Marketing_Campaigns, confirm CTR, CPC, and CPL match the definitions in your course materials. 3. On PnL_Margins, tie revenue and costs to gross margin and (optional) contribution margin using the labeled lines. 4. On Sales_Capacity_Model, adjust Model_Start_Date and ramp months to see how hiring timing affects first-year bookings. 5. Insert your own charts (recommended): CTR by campaign; stickiness over time; salary mix by position; top countries from Cities_Summary. 6. Dashboard pulls live KPIs from other sheets — refresh/recalc if you change inputs (F9). SHEET MAP (suggested order) Start_Here (you are here) → Marketing_Campaigns → PnL_Margins → Monthly_Unit_Economics → Stickiness → Sales_Capacity_Model → MLB_Salaries → MLB_by_Team → World_Cities_Raw → Cities_Summary → Lookup_Lab → Dashboard DATA SOURCES (CSV files in repo root) band-marketingmetric-quizzes-a.csv, smoothierock-*.csv, band-cpa-quiz.csv, band-marketingmetric-quizzes-b.csv, band-stickiness-quiz.csv, practice-quiz-salesforecast-topdown-data-csvfile.csv, albb-salaries-2003.csv, worldcities.csv

Sheet Marketing_Campaigns
A1: Ad campaign | B1: Impressions | C1: Clicks | D1: Spend | E1: Leads | F1: CTR | G1: CPC | H1: CPL
A2: Facebook | B2: 15000 | C2: 450 | D2: 315 | E2: 54 | F2: =IF(B2=0,"",C2/B2) | G2: =IF(C2=0,"",D2/C2) | H2: =IF(E2=0,"",D2/E2)
A3: Google search | B3: 20985 | C3: 314 | D3: 95 | E3: 76 | F3: =IF(B3=0,"",C3/B3) | G3: =IF(C3=0,"",D3/C3) | H3: =IF(E3=0,"",D3/E3)
A4: Bing search | B4: 85019 | C4: 983 | D4: 275 | E4: 83 | F4: =IF(B4=0,"",C4/B4) | G4: =IF(C4=0,"",D4/C4) | H4: =IF(E4=0,"",D4/E4)
A5: Google display | B5: 10453 | C5: 765 | D5: 114 | E5: 103 | F5: =IF(B5=0,"",C5/B5) | G5: =IF(C5=0,"",D5/C5) | H5: =IF(E5=0,"",D5/E5)
A6: Google YouTube | B6: 20875 | C6: 497 | D6: 112 | E6: 95 | F6: =IF(B6=0,"",C6/B6) | G6: =IF(C6=0,"",D6/C6) | H6: =IF(E6=0,"",D6/E6)
A7: TOTAL / AVG | B7: =SUM(B2:B6) | C7: =SUM(C2:C6) | D7: =SUM(D2:D6) | E7: =SUM(E2:E6) | F7: =IF(B7=0,"",C7/B7) | G7: =IF(C7=0,"",D7/C7) | H7: =IF(E7=0,"",D7/E7)

Sheet PnL_Margins
A1: Line item | B1: Amount ($)
A2: Total Revenue | B2: 500000
A3: Salary of staff | B3: 27500
A4: Cost of cash machine | B4: 534
A5: Cost of sales and marketing | B5: 7243
A6: Cost of fruits and vegetables | B6: 325000
A7: Cost of laptop | B7: 790
A8: Cost of smoothie cups, straws | B8: 10000
A9: Cost of furniture | B9: 5783
A10: Rent | B10: 10500
A11: Utilities | B11: 2000
A12: Units sold | B12: 60895
A14: Gross profit (Revenue − COGS fruits/veg) | B14: =B2-B6
A15: Gross margin % | B15: =IF(B2=0,"",B14/B2)
A16: Operating profit (Revenue − all costs above units) | B16: =B2-SUM(B3:B11)
A18: Contribution margin / unit (GP ÷ units) | B18: =IF(B12=0,"",B14/B12)

Sheet Monthly_Unit_Economics
A1: Month | B1: Marketing $ | C1: S&M Salaries $ | D1: Salary OH $ | E1: Leads | F1: Paid customers | G1: New paid (Δ) | H1: Cost / lead | I1: Mktg $ / new paid
A2: January | B2: 911 | C2: 3000 | D2: 375 | E2: 413 | F2: 300 | G2: — | H2: =IF(E2=0,"",B2/E2) | I2: =IF(OR(G2="—",G2=0),"",B2/G2)
A3: February | B3: 1200 | C3: 3000 | D3: 290 | E3: 520 | F3: 315 | G3: =F3-F2 | H3: =IF(E3=0,"",B3/E3) | I3: =IF(OR(G3="—",G3=0),"",B3/G3)
A4: March | B4: 875 | C4: 3000 | D4: 370 | E4: 536 | F4: 337 | G4: =F4-F3 | H4: =IF(E4=0,"",B4/E4) | I4: =IF(OR(G4="—",G4=0),"",B4/G4)

Sheet Stickiness
A1: Month | B1: DAU | C1: MAU | D1: Stickiness (DAU/MAU) | E1: Course check
A2: January | B2: 132 | C2: 396 | D2: =IF(C2=0,"",B2/C2) | E2: 0.33333333
A3: February | B3: 146 | C3: 548 | D3: =IF(C3=0,"",B3/C3) | E3: 0.26642336
A4: March | B4: 150 | C4: 480 | D4: =IF(C4=0,"",B4/C4) | E4: 0.3125
A5: April | B5: 162 | C5: 330 | D5: =IF(C5=0,"",B5/C5) | E5: 0.49090909
A6: May | B6: 177 | C6: 440 | D6: =IF(C6=0,"",B6/C6) | E6: 0.40227273
A7: June | B7: 190 | C7: 360 | D7: =IF(C7=0,"",B7/C7) | E7: 0.52777778

Sheet Sales_Capacity_Model
A1: Assumption | B1: Value
A2: Model_Start_Date (editable) | B2: 2025-01-01
A3: Opportunities closed / rep / year | B3: 53
A4: Avg PPU / month ($) | B4: 250
A5: Avg units per opportunity | B5: 56
A6: Avg contract months / opportunity | B6: 24
A7: Avg opportunity size — booking ($) | B7: 336000
A8: Annual booking capacity / rep ($) | B8: =B3*B7
A9: Seller ramp (months to full productivity) | B9: 4
A11: Sales employee | B11: Hire date | C11: Ramp end (EDATE) | D11: Yr-1 fraction (YEARFRAC) | E11: Yr-1 bookings ($)
A12: Sales person 1 | B12: =$B$2+30 | C12: =EDATE(B12,$B$9) | D12: =MIN(1,MAX(0,YEARFRAC(B12,DATE(2025,12,31),1))) | E12: =MIN($B$7,$B$7*MAX(0,YEARFRAC(C12,DATE(2025,12,31),1)))
A13: Sales person 2 | B13: =$B$2+60 | C13: =EDATE(B13,$B$9) | D13: =MIN(1,MAX(0,YEARFRAC(B13,DATE(2025,12,31),1))) | E13: =MIN($B$7,$B$7*MAX(0,YEARFRAC(C13,DATE(2025,12,31),1)))
A14: Sales person 3 | B14: =$B$2+90 | C14: =EDATE(B14,$B$9) | D14: =MIN(1,MAX(0,YEARFRAC(B14,DATE(2025,12,31),1))) | E14: =MIN($B$7,$B$7*MAX(0,YEARFRAC(C14,DATE(2025,12,31),1)))
A15: Total Yr-1 bookings (3 reps) | E15: =SUM(E12:E14)
A17: Note: Formulas are a simplified ramp model for practice; refine with monthly grids for production forecasts.

Sheet MLB_Salaries
A1: Team | B1: Last | C1: First | D1: Salary | E1: Position
A2: New York Yankees | B2: Acevedo | C2: Juan | D2: 900000 | E2: Pitcher
A3: New York Yankees | B3: Anderson | C3: Jason | D3: 300000 | E3: Pitcher
A4: New York Yankees | B4: Clemens | C4: Roger | D4: 10100000 | E4: Pitcher
A5: New York Yankees | B5: Contreras | C5: Jose | D5: 5500000 | E5: Pitcher
A6: New York Yankees | B6: Flaherty | C6: John | D6: 750000 | E6: Catcher
A7: New York Yankees | B7: Giambi | C7: Jason | D7: 11428571 | E7: First Baseman
A8: New York Yankees | B8: Hammond | C8: Chris | D8: 2200000 | E8: Pitcher
A9: New York Yankees | B9: Hitchcock | C9: Sterling | D9: 6000000 | E9: Pitcher
A10: New York Yankees | B10: Jeter | C10: Derek | D10: 15600000 | E10: Shortstop
A11: New York Yankees | B11: Johnson | C11: Nick | D11: 364100 | E11: First Baseman
A12: New York Yankees | B12: Karsay | C12: Steve | D12: 5000000 | E12: Pitcher
A13: New York Yankees | B13: Latham | C13: Chris | D13: 400000 | E13: Outfielder
... A382: Texas Rangers | B382: Zimmerman | C382: Jeff | D382: 3366667 | E382: Pitcher

Sheet MLB_by_Team
A1: Team | B1: Total payroll | C1: Players
A2: Anaheim Angels | B2: =SUMIFS(MLB_Salaries!$D:$D,MLB_Salaries!$A:$A,A2) | C2: =COUNTIF(MLB_Salaries!$A:$A,A2)
A3: Baltimore Orioles | B3: =SUMIFS(MLB_Salaries!$D:$D,MLB_Salaries!$A:$A,A3) | C3: =COUNTIF(MLB_Salaries!$A:$A,A3)
A4: Boston Red Sox | B4: =SUMIFS(MLB_Salaries!$D:$D,MLB_Salaries!$A:$A,A4) | C4: =COUNTIF(MLB_Salaries!$A:$A,A4)
A5: Chicago White Sox | B5: =SUMIFS(MLB_Salaries!$D:$D,MLB_Salaries!$A:$A,A5) | C5: =COUNTIF(MLB_Salaries!$A:$A,A5)
A6: Cleveland Indians | B6: =SUMIFS(MLB_Salaries!$D:$D,MLB_Salaries!$A:$A,A6) | C6: =COUNTIF(MLB_Salaries!$A:$A,A6)
A7: Detroit Tigers | B7: =SUMIFS(MLB_Salaries!$D:$D,MLB_Salaries!$A:$A,A7) | C7: =COUNTIF(MLB_Salaries!$A:$A,A7)
A8: Kansas City Royals | B8: =SUMIFS(MLB_Salaries!$D:$D,MLB_Salaries!$A:$A,A8) | C8: =COUNTIF(MLB_Salaries!$A:$A,A8)
A9: Minnesota Twins | B9: =SUMIFS(MLB_Salaries!$D:$D,MLB_Salaries!$A:$A,A9) | C9: =COUNTIF(MLB_Salaries!$A:$A,A9)
A10: New York Yankees | B10: =SUMIFS(MLB_Salaries!$D:$D,MLB_Salaries!$A:$A,A10) | C10: =COUNTIF(MLB_Salaries!$A:$A,A10)
A11: Oakland Athletics | B11: =SUMIFS(MLB_Salaries!$D:$D,MLB_Salaries!$A:$A,A11) | C11: =COUNTIF(MLB_Salaries!$A:$A,A11)
A12: Seattle Mariners | B12: =SUMIFS(MLB_Salaries!$D:$D,MLB_Salaries!$A:$A,A12) | C12: =COUNTIF(MLB_Salaries!$A:$A,A12)
A13: Tampa Bay Devil Rays | B13: =SUMIFS(MLB_Salaries!$D:$D,MLB_Salaries!$A:$A,A13) | C13: =COUNTIF(MLB_Salaries!$A:$A,A13)
... A15: Toronto Blue Jays | B15: =SUMIFS(MLB_Salaries!$D:$D,MLB_Salaries!$A:$A,A15) | C15: =COUNTIF(MLB_Salaries!$A:$A,A15)
A16: League total | B16: =SUM(B2:B15)

Sheet MLB_by_Position
A1: Position | B1: Headcount | C1: Total salary
A2: Catcher | B2: 36 | C2: 42216100
A3: First Baseman | B3: 27 | C3: 96967871
A4: Outfielder | B4: 66 | C4: 267301611
A5: Pitcher | B5: 180 | C5: 384323434
A6: Second Baseman | B6: 18 | C6: 23539500
A7: Shortstop | B7: 30 | C7: 88601467
A8: Third Baseman | B8: 24 | C8: 59072000

Sheet World_Cities_Raw
A1: City | B1: Country
A2: Rovaniemi | B2: Finland
A3: Steinkjer | B3: Norway
A4: Monterey | B4: United States of America
A5: Kuta | B5: Indonesia
A6: Lovec | B6: Bulgaria
A7: Moosonee | B7: Canada
A8: Gulkana | B8: United States of America
A9: Starorybnoye | B9: Russia
A10: Amol | B10: Iran
A11: Karema | B11: Tanzania
A12: Tayshet | B12: Russia
... A7251: Huangshi | B7251: China

Sheet Cities_Summary
A1: Country | B1: City count
A2: United States of America | B2: 724
A3: Russia | B3: 573
A4: China | B4: 393
A5: Brazil | B5: 388
A6: Canada | B6: 253
A7: Australia | B7: 222
A8: India | B8: 211
A9: Mexico | B9: 188
A10: Argentina | B10: 156
A11: Indonesia | B11: 105
A12: Kazakhstan | B12: 96
A13: Peru | B13: 89
... A41: Myanmar | B41: 37

Sheet Lookup_Lab
A1: Use INDEX/MATCH or XLOOKUP (Excel 365) against World_Cities_Raw to return the country for a city.
A3: Sample city (change me) | B3: Salzburg
A4: Country (your formula) | B4: =IFERROR(INDEX(World_Cities_Raw!$B:$B,MATCH(B3,World_Cities_Raw!$A:$A,0)),"not found")
A6: Count of cities in United States of America (try COUNTIF on World_Cities_Raw col B) | B6: =COUNTIF(World_Cities_Raw!$B:$B,"United States of America")

Sheet Dashboard
A1: KPI | B1: Value | C1: Source
A2: Blended CTR (all campaigns) | B2: =Marketing_Campaigns!F7 | C2: Marketing_Campaigns
A3: Total ad spend | B3: =Marketing_Campaigns!D7 | C3: Marketing_Campaigns
A4: Gross margin % | B4: =PnL_Margins!B15 | C4: PnL_Margins
A5: March stickiness (DAU/MAU) | B5: =Stickiness!D4 | C5: Stickiness
A6: Total Yr-1 sales bookings (3 reps) | B6: =Sales_Capacity_Model!E15 | C6: Sales_Capacity_Model
A7: League payroll (MLB sample) | B7: =MLB_by_Team!B16 | C7: MLB_by_Team
A8: Top country by city count | B8: =INDEX(Cities_Summary!$A$2:$A$41,MATCH(MAX(Cities_Summary!$B$2:$B$41),Cities_Summary!$B$2:$B$41,0)) | C8: Cities_Summary
